managesf/__init__.py
managesf/app.py
managesf/policy.py
managesf/sfauth.py
managesf/api/__init__.py
managesf/api/v2/__init__.py
managesf/api/v2/base.py
managesf/api/v2/managers.py
managesf/api/v2/resources/__init__.py
managesf/api/v2/resources/services/__init__.py
managesf/api/v2/resources/services/manageSF.py
managesf/cmds/__init__.py
managesf/cmds/keycloak.py
managesf/cmds/resources.py
managesf/controllers/__init__.py
managesf/controllers/introspection.py
managesf/controllers/root.py
managesf/controllers/api/__init__.py
managesf/controllers/api/v2/__init__.py
managesf/controllers/api/v2/base.py
managesf/controllers/api/v2/configurations.py
managesf/controllers/api/v2/resources.py
managesf/lib/__init__.py
managesf/lib/common.py
managesf/lib/auth/__init__.py
managesf/lib/auth/base.py
managesf/lib/auth/keycloak.py
managesf/model/__init__.py
managesf/model/yamlbkd/__init__.py
managesf/model/yamlbkd/engine.py
managesf/model/yamlbkd/resource.py
managesf/model/yamlbkd/yamlbackend.py
managesf/model/yamlbkd/resources/__init__.py
managesf/model/yamlbkd/resources/connection.py
managesf/model/yamlbkd/resources/dummy.py
managesf/model/yamlbkd/resources/gitacls.py
managesf/model/yamlbkd/resources/gitrepository.py
managesf/model/yamlbkd/resources/group.py
managesf/model/yamlbkd/resources/project.py
managesf/model/yamlbkd/resources/tenant.py
managesf/policies/__init__.py
managesf/policies/base.py
managesf/policies/config.py
managesf/policies/hooks.py
managesf/policies/localuser.py
managesf/policies/resources.py
managesf/policies/services_users.py
managesf/services/__init__.py
managesf/services/base.py
managesf/services/exceptions.py
managesf/services/gerrit/__init__.py
managesf/services/gerrit/group.py
managesf/services/gerrit/project.py
managesf/services/gerrit/review.py
managesf/services/gerrit/user.py
managesf/services/gerrit/utils.py
managesf/services/keycloak/__init__.py
managesf/tests/__init__.py
managesf/tests/resources_test_utils.py
managesf/tests/test_apiv2.py
managesf-0.32.1.dist-info/AUTHORS
managesf-0.32.1.dist-info/LICENSE
managesf-0.32.1.dist-info/METADATA
managesf-0.32.1.dist-info/WHEEL
managesf-0.32.1.dist-info/dependency_links.txt
managesf-0.32.1.dist-info/entry_points.txt
managesf-0.32.1.dist-info/pbr.json
managesf-0.32.1.dist-info/top_level.txt
managesf-0.32.1.dist-info/RECORD
