Metadata-Version: 2.1
Name: managesf
Version: 0.32.1
Summary: Software Factory REST API
License-File: LICENSE
Requires-Dist: pbr
Requires-Dist: pecan
Requires-Dist: WebOb
Requires-Dist: requests
Requires-Dist: basicauth (==0.4.1)
Requires-Dist: sqlalchemy (<=2.0.0)
Requires-Dist: urllib3
Requires-Dist: sphinx
Requires-Dist: PyYAML
Requires-Dist: stevedore
Requires-Dist: PyMySQL
Requires-Dist: six
Requires-Dist: oslo.policy
Requires-Dist: deepdiff (==3.3.0)
Requires-Dist: GitPython
Requires-Dist: webtest
Requires-Dist: pynotedb
